main.py
heygrindror-0.5.dist-info/METADATA
heygrindror-0.5.dist-info/WHEEL
heygrindror-0.5.dist-info/top_level.txt
heygrindror-0.5.dist-info/RECORD
