Metadata-Version: 2.1
Name: heygrindror
Version: 0.5
Summary: powerfull tool to grinding on discord
Author-email: umyams <umyamc@gmail.com>
Project-URL: Homepage, https://github.com/umyams/heygrindror
Project-URL: repository, https://github.com/umyams/heygrindror
Classifier: Programming Language :: Python :: 3
Classifier: License :: OSI Approved :: MIT License
Classifier: Operating System :: OS Independent
Requires-Python: >=3.8
Requires-Dist: heyreplit ==0.8
Requires-Dist: heynotbot ==1.2
